llvm_python-0.0.1b1.dist-info/METADATA
llvm_python-0.0.1b1.dist-info/RECORD
llvm_python-0.0.1b1.dist-info/top_level.txt
llvm_python-0.0.1b1.dist-info/WHEEL
llvm_python/__init__.py
llvm_python/utils.py
llvm_python/_llvm_python.cpython-38-x86_64-linux-gnu.so
llvm_python/ir/type.py
llvm_python/ir/argument.py
llvm_python/ir/module.py
llvm_python/ir/__init__.py
llvm_python/ir/instruction.py
llvm_python/ir/tools.py
llvm_python/ir/value.py
llvm_python/ir/function.py
llvm_python/ir/block.py
llvm_python.libs/libtinfo-3a2cb85b.so.6.1
