Metadata-Version: 2.1
Name: llvm_python
Version: 0.0.1b1
Summary: A library for analyzing LLVM IR in Python
Home-page: https://github.com/Papr1ka/llvm_python
Author: Papr1ka
Author-email: kirillpavlov4214@gmail.com
License: MIT
Keywords: llvm,analysis,ir,intermediate,presentation,representation,compiler,parser
Classifier: Development Status :: 4 - Beta
Classifier: Operating System :: Microsoft :: Windows
Classifier: Operating System :: POSIX
Classifier: Intended Audience :: Developers
Classifier: Intended Audience :: Education
Classifier: Intended Audience :: Science/Research
Classifier: Topic :: Scientific/Engineering
Classifier: Topic :: Software Development :: Libraries
Classifier: License :: OSI Approved :: MIT License
Classifier: Natural Language :: English
Classifier: Programming Language :: Python :: 3
Classifier: Programming Language :: Python :: 3.7
Classifier: Programming Language :: Python :: 3.8
Classifier: Programming Language :: Python :: 3.9
Classifier: Programming Language :: Python :: 3.10
Classifier: Programming Language :: Python :: 3.11
Classifier: Programming Language :: Python :: 3.12
Requires-Python: >=3.7
